[{"absolute_file_path": "E:\\Music\\Larkin Poe\\2021\\Folder.auCDtect.txt", "file_format": "txt", "file_name": "Folder.auCDtect", "file_author": null, "release_date": null, "date_added": null, "publisher": null, "genre": null, "date_most_recently_opened": null, "country_of_origin": null, "language": null, "file_size": null}, {"absolute_file_path": "E:\\Music\\Larkin Poe\\2021\\foo_dr.txt", "file_format": "txt", "file_name": "foo_dr", "file_author": null, "release_date": null, "date_added": null, "publisher": null, "genre": null, "date_most_recently_opened": null, "country_of_origin": null, "language": null, "file_size": null}, {"absolute_file_path": "E:\\Music\\Larkin Poe\\Reskinned (2016) FLAC\\Folder.auCDtect.txt", "file_format": "txt", "file_name": "Folder.auCDtect", "file_author": null, "release_date": null, "date_added": null, "publisher": null, "genre": null, "date_most_recently_opened": null, "country_of_origin": null, "language": null, "file_size": null}, {"absolute_file_path": "E:\\Music\\Larkin Poe\\Reskinned (2016) FLAC\\foo_DR7.txt", "file_format": "txt", "file_name": "foo_DR7", "file_author": null, "release_date": null, "date_added": null, "publisher": null, "genre": null, "date_most_recently_opened": null, "country_of_origin": null, "language": null, "file_size": null}, {"absolute_file_path": null, "file_format": "mp3_album", "file_name": "Spring", "file_author": "Larkin Poe", "file_cover": null, "release_date": "2010", "album_tracks_dictionary": [{"track_album_title": "Spring", "file_album_artist": "Larkin Poe", "file_album_total_track_number": "", "file_album_total_disk_number": "", "file_album_release_year": "2010", "track_title": "Long Hard Fall", "track_artist": "Larkin Poe", "track_number": "", "track_genre": "'Folk-Rock, Americana, Roots Rock'", "track_lenght": "02:43", "absolute_file_path": "E:\\Music\\Larkin Poe\\2011 Band For All Seasons (4CD) (L)\\CD 1. Spring\\01. Long Hard Fall.mp3", "file_format": "mp3"}, {"track_album_title": "Spring", "file_album_artist": "Larkin Poe", "file_album_total_track_number": "", "file_album_total_disk_number": "", "file_album_release_year": "2010", "track_title": "We Intertwine", "track_artist": "Larkin Poe", "track_number": "", "track_genre": "'Folk-Rock, Americana, Roots Rock'", "track_lenght": "03:56", "absolute_file_path": "E:\\Music\\Larkin Poe\\2011 Band For All Seasons (4CD) (L)\\CD 1. Spring\\02. We Intertwine.mp3", "file_format": "mp3"}, {"track_album_title": "Spring", "file_album_artist": "Larkin Poe", "file_album_total_track_number": "", "file_album_total_disk_number": "", "file_album_release_year": "2010", "track_title": "Burglary", "track_artist": "Larkin Poe", "track_number": "", "track_genre": "'Folk-Rock, Americana, Roots Rock'", "track_lenght": "03:42", "absolute_file_path": "E:\\Music\\Larkin Poe\\2011 Band For All Seasons (4CD) (L)\\CD 1. Spring\\03. Burglary.mp3", "file_format": "mp3"}, {"track_album_title": "Spring", "file_album_artist": "Larkin Poe", "file_album_total_track_number": "", "file_album_total_disk_number": "", "file_album_release_year": "2010", "track_title": "To Myself", "track_artist": "Larkin Poe", "track_number": "", "track_genre": "'Folk-Rock, Americana, Roots Rock'", "track_lenght": "03:48", "absolute_file_path": "E:\\Music\\Larkin Poe\\2011 Band For All Seasons (4CD) (L)\\CD 1. Spring\\04. To Myself.mp3", "file_format": "mp3"}, {"track_album_title": "Spring", "file_album_artist": "Larkin Poe", "file_album_total_track_number": "", "file_album_total_disk_number": "", "file_album_release_year": "2010", "track_title": "Shadows Of Ourselves", "track_artist": "Larkin Poe", "track_number": "", "track_genre": "'Folk-Rock, Americana, Roots Rock'", "track_lenght": "03:59", "absolute_file_path": "E:\\Music\\Larkin Poe\\2011 Band For All Seasons (4CD) (L)\\CD 1. Spring\\05. Shadows Of Ourselves.mp3", "file_format": "mp3"}, {"track_album_title": "Spring", "file_album_artist": "Larkin Poe", "file_album_total_track_number": "", "file_album_total_disk_number": "", "file_album_release_year": "2010", "track_title": "The Principle Of Silver Lining", "track_artist": "Larkin Poe", "track_number": "", "track_genre": "'Folk-Rock, Americana, Roots Rock'", "track_lenght": "05:39", "absolute_file_path": "E:\\Music\\Larkin Poe\\2011 Band For All Seasons (4CD) (L)\\CD 1. Spring\\06. The Principle Of Silver Lining.mp3", "file_format": "mp3"}, {"track_album_title": "Spring", "file_album_artist": "Larkin Poe", "file_album_total_track_number": "", "file_album_total_disk_number": "", "file_album_release_year": "2010", "track_title": "Ball And Chain", "track_artist": "Larkin Poe", "track_number": "", "track_genre": "'Folk-Rock, Americana, Roots Rock'", "track_lenght": "03:15", "absolute_file_path": "E:\\Music\\Larkin Poe\\2011 Band For All Seasons (4CD) (L)\\CD 1. Spring\\07. Ball And Chain.mp3", "file_format": "mp3"}, {"track_album_title": "Spring", "file_album_artist": "Larkin Poe", "file_album_total_track_number": "", "file_album_total_disk_number": "", "file_album_release_year": "2010", "track_title": "Nothin' But Air", "track_artist": "Larkin Poe", "track_number": "", "track_genre": "'Folk-Rock, Americana, Roots Rock'", "track_lenght": "03:32", "absolute_file_path": "E:\\Music\\Larkin Poe\\2011 Band For All Seasons (4CD) (L)\\CD 1. Spring\\08. Nothin' But Air.mp3", "file_format": "mp3"}, {"track_album_title": "Spring", "file_album_artist": "Larkin Poe", "file_album_total_track_number": "", "file_album_total_disk_number": "", "file_album_release_year": "2010", "track_title": "Fairbanks Alaska", "track_artist": "Larkin Poe", "track_number": "", "track_genre": "'Folk-Rock, Americana, Roots Rock'", "track_lenght": "03:05", "absolute_file_path": "E:\\Music\\Larkin Poe\\2011 Band For All Seasons (4CD) (L)\\CD 1. Spring\\09. Fairbanks Alaska.mp3", "file_format": "mp3"}], "date_added": null, "publisher": null, "album_genre": ["'Folk-Rock, Americana, Roots Rock'"], "date_most_recently_opened": null, "country_of_origin": null, "language": null, "file_size": null}, {"absolute_file_path": null, "file_format": "mp3_album", "file_name": "Fall", "file_author": "Larkin Poe", "file_cover": null, "release_date": "2010", "album_tracks_dictionary": [{"track_album_title": "Fall", "file_album_artist": "Larkin Poe", "file_album_total_track_number": "", "file_album_total_disk_number": "", "file_album_release_year": "2010", "track_title": "Memories", "track_artist": "Larkin Poe", "track_number": "", "track_genre": "'Folk-Rock, Americana, Roots Rock'", "track_lenght": "04:12", "absolute_file_path": "E:\\Music\\Larkin Poe\\2011 Band For All Seasons (4CD) (L)\\CD 3. Fall\\01. Memories.mp3", "file_format": "mp3"}, {"track_album_title": "Fall", "file_album_artist": "Larkin Poe", "file_album_total_track_number": "", "file_album_total_disk_number": "", "file_album_release_year": "2010", "track_title": "Horse Shoes & Hand Grenades", "track_artist": "Larkin Poe", "track_number": "", "track_genre": "'Folk-Rock, Americana, Roots Rock'", "track_lenght": "03:08", "absolute_file_path": "E:\\Music\\Larkin Poe\\2011 Band For All Seasons (4CD) (L)\\CD 3. Fall\\02. Horse Shoes & Hand Grenades.mp3", "file_format": "mp3"}, {"track_album_title": "Fall", "file_album_artist": "Larkin Poe", "file_album_total_track_number": "", "file_album_total_disk_number": "", "file_album_release_year": "2010", "track_title": "Just In Case", "track_artist": "Larkin Poe", "track_number": "", "track_genre": "'Folk-Rock, Americana, Roots Rock'", "track_lenght": "04:44", "absolute_file_path": "E:\\Music\\Larkin Poe\\2011 Band For All Seasons (4CD) (L)\\CD 3. Fall\\03. Just In Case.mp3", "file_format": "mp3"}, {"track_album_title": "Fall", "file_album_artist": "Larkin Poe", "file_album_total_track_number": "", "file_album_total_disk_number": "", "file_album_release_year": "2010", "track_title": "Spooked", "track_artist": "Larkin Poe", "track_number": "", "track_genre": "'Folk-Rock, Americana, Roots Rock'", "track_lenght": "04:20", "absolute_file_path": "E:\\Music\\Larkin Poe\\2011 Band For All Seasons (4CD) (L)\\CD 3. Fall\\04. Spooked.mp3", "file_format": "mp3"}, {"track_album_title": "Fall", "file_album_artist": "Larkin Poe", "file_album_total_track_number": "", "file_album_total_disk_number": "", "file_album_release_year": "2010", "track_title": "It Gets Better As You Go", "track_artist": "Larkin Poe", "track_number": "", "track_genre": "'Folk-Rock, Americana, Roots Rock'", "track_lenght": "02:50", "absolute_file_path": "E:\\Music\\Larkin Poe\\2011 Band For All Seasons (4CD) (L)\\CD 3. Fall\\05. It Gets Better As You Go.mp3", "file_format": "mp3"}, {"track_album_title": "Fall", "file_album_artist": "Larkin Poe", "file_album_total_track_number": "", "file_album_total_disk_number": "", "file_album_release_year": "2010", "track_title": "Fall From The Tree", "track_artist": "Larkin Poe", "track_number": "", "track_genre": "'Folk-Rock, Americana, Roots Rock'", "track_lenght": "05:47", "absolute_file_path": "E:\\Music\\Larkin Poe\\2011 Band For All Seasons (4CD) (L)\\CD 3. Fall\\06. Fall From The Tree.mp3", "file_format": "mp3"}], "date_added": null, "publisher": null, "album_genre": ["'Folk-Rock, Americana, Roots Rock'"], "date_most_recently_opened": null, "country_of_origin": null, "language": null, "file_size": null}, {"absolute_file_path": null, "file_format": "mp3_album", "file_name": "Thick As Thieves", "file_author": "Larkin Poe", "file_cover": null, "release_date": "2012", "album_tracks_dictionary": [{"track_album_title": "Thick As Thieves", "file_album_artist": "Larkin Poe", "file_album_total_track_number": "", "file_album_total_disk_number": "", "file_album_release_year": "2012", "track_title": "Fox", "track_artist": "Larkin Poe", "track_number": "", "track_genre": "'Folk-Rock, Americana, Roots Rock'", "track_lenght": "03:20", "absolute_file_path": "E:\\Music\\Larkin Poe\\EP, Singles\\2012 Thick As Thieves (EP) (VBR 226-264)\\01. Fox.mp3", "file_format": "mp3"}, {"track_album_title": "Thick As Thieves", "file_album_artist": "Larkin Poe", "file_album_total_track_number": "", "file_album_total_disk_number": "", "file_album_release_year": "2012", "track_title": "Play On", "track_artist": "Larkin Poe", "track_number": "", "track_genre": "'Folk-Rock, Americana, Roots Rock'", "track_lenght": "03:38", "absolute_file_path": "E:\\Music\\Larkin Poe\\EP, Singles\\2012 Thick As Thieves (EP) (VBR 226-264)\\02. Play On.mp3", "file_format": "mp3"}, {"track_album_title": "Thick As Thieves", "file_album_artist": "Larkin Poe", "file_album_total_track_number": "", "file_album_total_disk_number": "", "file_album_release_year": "2012", "track_title": "Love Or Money", "track_artist": "Larkin Poe", "track_number": "", "track_genre": "'Folk-Rock, Americana, Roots Rock'", "track_lenght": "03:43", "absolute_file_path": "E:\\Music\\Larkin Poe\\EP, Singles\\2012 Thick As Thieves (EP) (VBR 226-264)\\03. Love Or Money.mp3", "file_format": "mp3"}, {"track_album_title": "Thick As Thieves", "file_album_artist": "Larkin Poe", "file_album_total_track_number": "", "file_album_total_disk_number": "", "file_album_release_year": "2012", "track_title": "Celebrate", "track_artist": "Larkin Poe", "track_number": "", "track_genre": "'Folk-Rock, Americana, Roots Rock'", "track_lenght": "02:56", "absolute_file_path": "E:\\Music\\Larkin Poe\\EP, Singles\\2012 Thick As Thieves (EP) (VBR 226-264)\\04. Celebrate.mp3", "file_format": "mp3"}, {"track_album_title": "Thick As Thieves", "file_album_artist": "Larkin Poe", "file_album_total_track_number": "", "file_album_total_disk_number": "", "file_album_release_year": "2012", "track_title": "Make It Hurt", "track_artist": "Larkin Poe", "track_number": "", "track_genre": "'Folk-Rock, Americana, Roots Rock'", "track_lenght": "04:33", "absolute_file_path": "E:\\Music\\Larkin Poe\\EP, Singles\\2012 Thick As Thieves (EP) (VBR 226-264)\\05. Make It Hurt.mp3", "file_format": "mp3"}, {"track_album_title": "Thick As Thieves", "file_album_artist": "Larkin Poe", "file_album_total_track_number": "", "file_album_total_disk_number": "", "file_album_release_year": "2012", "track_title": "On The Fritz", "track_artist": "Larkin Poe", "track_number": "", "track_genre": "'Folk-Rock, Americana, Roots Rock'", "track_lenght": "03:19", "absolute_file_path": "E:\\Music\\Larkin Poe\\EP, Singles\\2012 Thick As Thieves (EP) (VBR 226-264)\\06. On The Fritz.mp3", "file_format": "mp3"}, {"track_album_title": "Thick As Thieves", "file_album_artist": "Larkin Poe", "file_album_total_track_number": "", "file_album_total_disk_number": "", "file_album_release_year": "2012", "track_title": "Russian Roulette", "track_artist": "Larkin Poe", "track_number": "", "track_genre": "'Folk-Rock, Americana, Roots Rock'", "track_lenght": "03:43", "absolute_file_path": "E:\\Music\\Larkin Poe\\EP, Singles\\2012 Thick As Thieves (EP) (VBR 226-264)\\07. Russian Roulette.mp3", "file_format": "mp3"}], "date_added": null, "publisher": null, "album_genre": ["'Folk-Rock, Americana, Roots Rock'"], "date_most_recently_opened": null, "country_of_origin": null, "language": null, "file_size": null}, {"absolute_file_path": null, "file_format": "mp3_album", "file_name": "Self Made Man", "file_author": "Larkin Poe", "file_cover": null, "release_date": "", "album_tracks_dictionary": [{"track_album_title": "Self Made Man", "file_album_artist": "Larkin Poe", "file_album_total_track_number": "", "file_album_total_disk_number": "", "file_album_release_year": "", "track_title": "She's A Self Made Man", "track_artist": "Larkin Poe", "track_number": "", "track_genre": "'Rock'", "track_lenght": "03:01", "absolute_file_path": "E:\\Music\\Larkin Poe\\Self Made Man\\01 She's A Self Made Man.mp3", "file_format": "mp3"}, {"track_album_title": "Self Made Man", "file_album_artist": "Larkin Poe", "file_album_total_track_number": "", "file_album_total_disk_number": "", "file_album_release_year": "", "track_title": "Holy Ghost Fire", "track_artist": "Larkin Poe", "track_number": "", "track_genre": "'Rock'", "track_lenght": "03:22", "absolute_file_path": "E:\\Music\\Larkin Poe\\Self Made Man\\02 Holy Ghost Fire.mp3", "file_format": "mp3"}, {"track_album_title": "Self Made Man", "file_album_artist": "Larkin Poe", "file_album_total_track_number": "", "file_album_total_disk_number": "", "file_album_release_year": "", "track_title": "Keep Diggin'", "track_artist": "Larkin Poe", "track_number": "", "track_genre": "'Rock'", "track_lenght": "03:13", "absolute_file_path": "E:\\Music\\Larkin Poe\\Self Made Man\\03 Keep Diggin'.mp3", "file_format": "mp3"}, {"track_album_title": "Self Made Man", "file_album_artist": "Larkin Poe", "file_album_total_track_number": "", "file_album_total_disk_number": "", "file_album_release_year": "", "track_title": "Back Down South", "track_artist": "Larkin Poe", "track_number": "", "track_genre": "'Rock'", "track_lenght": "03:54", "absolute_file_path": "E:\\Music\\Larkin Poe\\Self Made Man\\04 Back Down South.mp3", "file_format": "mp3"}, {"track_album_title": "Self Made Man", "file_album_artist": "Larkin Poe", "file_album_total_track_number": "", "file_album_total_disk_number": "", "file_album_release_year": "", "track_title": "Tears Of Blue To Gold", "track_artist": "Larkin Poe", "track_number": "", "track_genre": "'Rock'", "track_lenght": "03:12", "absolute_file_path": "E:\\Music\\Larkin Poe\\Self Made Man\\05 Tears Of Blue To Gold.mp3", "file_format": "mp3"}, {"track_album_title": "Self Made Man", "file_album_artist": "Larkin Poe", "file_album_total_track_number": "", "file_album_total_disk_number": "", "file_album_release_year": "", "track_title": "God Moves On The Water", "track_artist": "Larkin Poe", "track_number": "", "track_genre": "'Rock'", "track_lenght": "02:44", "absolute_file_path": "E:\\Music\\Larkin Poe\\Self Made Man\\06 God Moves On The Water.mp3", "file_format": "mp3"}, {"track_album_title": "Self Made Man", "file_album_artist": "Larkin Poe", "file_album_total_track_number": "", "file_album_total_disk_number": "", "file_album_release_year": "", "track_title": "Every Bird That Flies", "track_artist": "Larkin Poe", "track_number": "", "track_genre": "'Rock'", "track_lenght": "03:40", "absolute_file_path": "E:\\Music\\Larkin Poe\\Self Made Man\\07 Every Bird That Flies.mp3", "file_format": "mp3"}, {"track_album_title": "Self Made Man", "file_album_artist": "Larkin Poe", "file_album_total_track_number": "", "file_album_total_disk_number": "", "file_album_release_year": "", "track_title": "Scorpion", "track_artist": "Larkin Poe", "track_number": "", "track_genre": "'Rock'", "track_lenght": "03:12", "absolute_file_path": "E:\\Music\\Larkin Poe\\Self Made Man\\08 Scorpion.mp3", "file_format": "mp3"}, {"track_album_title": "Self Made Man", "file_album_artist": "Larkin Poe", "file_album_total_track_number": "", "file_album_total_disk_number": "", "file_album_release_year": "", "track_title": "Danger Angel", "track_artist": "Larkin Poe", "track_number": "", "track_genre": "'Rock'", "track_lenght": "02:27", "absolute_file_path": "E:\\Music\\Larkin Poe\\Self Made Man\\09 Danger Angel.mp3", "file_format": "mp3"}, {"track_album_title": "Self Made Man", "file_album_artist": "Larkin Poe", "file_album_total_track_number": "", "file_album_total_disk_number": "", "file_album_release_year": "", "track_title": "Ex-Con", "track_artist": "Larkin Poe", "track_number": "", "track_genre": "'Rock'", "track_lenght": "03:56", "absolute_file_path": "E:\\Music\\Larkin Poe\\Self Made Man\\10 Ex-Con.mp3", "file_format": "mp3"}, {"track_album_title": "Self Made Man", "file_album_artist": "Larkin Poe", "file_album_total_track_number": "", "file_album_total_disk_number": "", "file_album_release_year": "", "track_title": "Easy Street", "track_artist": "Larkin Poe", "track_number": "", "track_genre": "'Rock'", "track_lenght": "02:17", "absolute_file_path": "E:\\Music\\Larkin Poe\\Self Made Man\\11 Easy Street.mp3", "file_format": "mp3"}], "date_added": null, "publisher": null, "album_genre": ["'Rock'"], "date_most_recently_opened": null, "country_of_origin": null, "language": null, "file_size": null}, {"absolute_file_path": null, "file_format": "mp3_album", "file_name": "Summer", "file_author": "Larkin Poe", "file_cover": null, "release_date": "2010", "album_tracks_dictionary": [{"track_album_title": "Summer", "file_album_artist": "Larkin Poe", "file_album_total_track_number": "", "file_album_total_disk_number": "", "file_album_release_year": "2010", "track_title": "Praying for the bell", "track_artist": "Larkin Poe", "track_number": "", "track_genre": "'Folk-Rock, Americana, Roots Rock'", "track_lenght": "03:05", "absolute_file_path": "E:\\Music\\Larkin Poe\\2011 Band For All Seasons (4CD) (L)\\CD 2. Summer\\01. Praying for the bell.mp3", "file_format": "mp3"}, {"track_album_title": "Summer", "file_album_artist": "Larkin Poe", "file_album_total_track_number": "", "file_album_total_disk_number": "", "file_album_release_year": "2010", "track_title": "Sea song", "track_artist": "Larkin Poe", "track_number": "", "track_genre": "'Folk-Rock, Americana, Roots Rock'", "track_lenght": "02:44", "absolute_file_path": "E:\\Music\\Larkin Poe\\2011 Band For All Seasons (4CD) (L)\\CD 2. Summer\\02. Sea song.mp3", "file_format": "mp3"}, {"track_album_title": "Summer", "file_album_artist": "Larkin Poe", "file_album_total_track_number": "", "file_album_total_disk_number": "", "file_album_release_year": "2010", "track_title": "Wrestling a stranger", "track_artist": "Larkin Poe", "track_number": "", "track_genre": "'Folk-Rock, Americana, Roots Rock'", "track_lenght": "03:32", "absolute_file_path": "E:\\Music\\Larkin Poe\\2011 Band For All Seasons (4CD) (L)\\CD 2. Summer\\03. Wrestling a stranger.mp3", "file_format": "mp3"}, {"track_album_title": "Summer", "file_album_artist": "Larkin Poe", "file_album_total_track_number": "", "file_album_total_disk_number": "", "file_album_release_year": "2010", "track_title": "Natalie", "track_artist": "Larkin Poe", "track_number": "", "track_genre": "'Folk-Rock, Americana, Roots Rock'", "track_lenght": "02:56", "absolute_file_path": "E:\\Music\\Larkin Poe\\2011 Band For All Seasons (4CD) (L)\\CD 2. Summer\\04. Natalie.mp3", "file_format": "mp3"}, {"track_album_title": "Summer", "file_album_artist": "Larkin Poe", "file_album_total_track_number": "", "file_album_total_disk_number": "", "file_album_release_year": "2010", "track_title": "Enough for you", "track_artist": "Larkin Poe", "track_number": "", "track_genre": "'Folk-Rock, Americana, Roots Rock'", "track_lenght": "03:25", "absolute_file_path": "E:\\Music\\Larkin Poe\\2011 Band For All Seasons (4CD) (L)\\CD 2. Summer\\05. Enough for you.mp3", "file_format": "mp3"}, {"track_album_title": "Summer", "file_album_artist": "Larkin Poe", "file_album_total_track_number": "", "file_album_total_disk_number": "", "file_album_release_year": "2010", "track_title": "By the pier", "track_artist": "Larkin Poe", "track_number": "", "track_genre": "'Folk-Rock, Americana, Roots Rock'", "track_lenght": "03:01", "absolute_file_path": "E:\\Music\\Larkin Poe\\2011 Band For All Seasons (4CD) (L)\\CD 2. Summer\\06. By the pier.mp3", "file_format": "mp3"}, {"track_album_title": "Summer", "file_album_artist": "Larkin Poe", "file_album_total_track_number": "", "file_album_total_disk_number": "", "file_album_release_year": "2010", "track_title": "In my time of dying (live)", "track_artist": "Larkin Poe", "track_number": "", "track_genre": "'Folk-Rock, Americana, Roots Rock'", "track_lenght": "03:45", "absolute_file_path": "E:\\Music\\Larkin Poe\\2011 Band For All Seasons (4CD) (L)\\CD 2. Summer\\07. In my time of dying (live).mp3", "file_format": "mp3"}, {"track_album_title": "Summer", "file_album_artist": "Larkin Poe", "file_album_total_track_number": "", "file_album_total_disk_number": "", "file_album_release_year": "2010", "track_title": "Principle of silver lining (live)", "track_artist": "Larkin Poe", "track_number": "", "track_genre": "'Folk-Rock, Americana, Roots Rock'", "track_lenght": "07:23", "absolute_file_path": "E:\\Music\\Larkin Poe\\2011 Band For All Seasons (4CD) (L)\\CD 2. Summer\\08. Principle of silver lining (live).mp3", "file_format": "mp3"}, {"track_album_title": "Summer", "file_album_artist": "Larkin Poe", "file_album_total_track_number": "", "file_album_total_disk_number": "", "file_album_release_year": "2010", "track_title": "Teardrop (live)", "track_artist": "Larkin Poe", "track_number": "", "track_genre": "'Folk-Rock, Americana, Roots Rock'", "track_lenght": "04:37", "absolute_file_path": "E:\\Music\\Larkin Poe\\2011 Band For All Seasons (4CD) (L)\\CD 2. Summer\\09. Teardrop (live).mp3", "file_format": "mp3"}], "date_added": null, "publisher": null, "album_genre": ["'Folk-Rock, Americana, Roots Rock'"], "date_most_recently_opened": null, "country_of_origin": null, "language": null, "file_size": null}, {"absolute_file_path": null, "file_format": "mp3_album", "file_name": "Winter", "file_author": "Larkin Poe", "file_cover": null, "release_date": "2011", "album_tracks_dictionary": [{"track_album_title": "Winter", "file_album_artist": "Larkin Poe", "file_album_total_track_number": "", "file_album_total_disk_number": "", "file_album_release_year": "2011", "track_title": "Desert Dream", "track_artist": "Larkin Poe", "track_number": "", "track_genre": "'Folk-Rock, Americana, Roots Rock'", "track_lenght": "02:54", "absolute_file_path": "E:\\Music\\Larkin Poe\\2011 Band For All Seasons (4CD) (L)\\CD 4. Winter\\01. Desert Dream.mp3", "file_format": "mp3"}, {"track_album_title": "Winter", "file_album_artist": "Larkin Poe", "file_album_total_track_number": "", "file_album_total_disk_number": "", "file_album_release_year": "2011", "track_title": "Taller Far Than A Tall Man", "track_artist": "Larkin Poe", "track_number": "", "track_genre": "'Folk-Rock, Americana, Roots Rock'", "track_lenght": "04:05", "absolute_file_path": "E:\\Music\\Larkin Poe\\2011 Band For All Seasons (4CD) (L)\\CD 4. Winter\\02. Taller Far Than A Tall Man.mp3", "file_format": "mp3"}, {"track_album_title": "Winter", "file_album_artist": "Larkin Poe", "file_album_total_track_number": "", "file_album_total_disk_number": "", "file_album_release_year": "2011", "track_title": "Cure For The Common Cold", "track_artist": "Larkin Poe", "track_number": "", "track_genre": "'Folk-Rock, Americana, Roots Rock'", "track_lenght": "03:58", "absolute_file_path": "E:\\Music\\Larkin Poe\\2011 Band For All Seasons (4CD) (L)\\CD 4. Winter\\03. Cure For The Common Cold.mp3", "file_format": "mp3"}, {"track_album_title": "Winter", "file_album_artist": "Larkin Poe", "file_album_total_track_number": "", "file_album_total_disk_number": "", "file_album_release_year": "2011", "track_title": "Word From The Wise", "track_artist": "Larkin Poe", "track_number": "", "track_genre": "'Folk-Rock, Americana, Roots Rock'", "track_lenght": "03:47", "absolute_file_path": "E:\\Music\\Larkin Poe\\2011 Band For All Seasons (4CD) (L)\\CD 4. Winter\\04. Word From The Wise.mp3", "file_format": "mp3"}, {"track_album_title": "Winter", "file_album_artist": "Larkin Poe", "file_album_total_track_number": "", "file_album_total_disk_number": "", "file_album_release_year": "2011", "track_title": "Free Like A Bird", "track_artist": "Larkin Poe", "track_number": "", "track_genre": "'Folk-Rock, Americana, Roots Rock'", "track_lenght": "03:58", "absolute_file_path": "E:\\Music\\Larkin Poe\\2011 Band For All Seasons (4CD) (L)\\CD 4. Winter\\05. Free Like A Bird.mp3", "file_format": "mp3"}, {"track_album_title": "Winter", "file_album_artist": "Larkin Poe", "file_album_total_track_number": "", "file_album_total_disk_number": "", "file_album_release_year": "2011", "track_title": "Trance", "track_artist": "Larkin Poe", "track_number": "", "track_genre": "'Folk-Rock, Americana, Roots Rock'", "track_lenght": "03:22", "absolute_file_path": "E:\\Music\\Larkin Poe\\2011 Band For All Seasons (4CD) (L)\\CD 4. Winter\\06. Trance.mp3", "file_format": "mp3"}, {"track_album_title": "Winter", "file_album_artist": "Larkin Poe", "file_album_total_track_number": "", "file_album_total_disk_number": "", "file_album_release_year": "2011", "track_title": "This Girl", "track_artist": "Larkin Poe", "track_number": "", "track_genre": "'Folk-Rock, Americana, Roots Rock'", "track_lenght": "03:41", "absolute_file_path": "E:\\Music\\Larkin Poe\\2011 Band For All Seasons (4CD) (L)\\CD 4. Winter\\07. This Girl.mp3", "file_format": "mp3"}], "date_added": null, "publisher": null, "album_genre": ["'Folk-Rock, Americana, Roots Rock'"], "date_most_recently_opened": null, "country_of_origin": null, "language": null, "file_size": null}, {"absolute_file_path": null, "file_format": "mp3_album", "file_name": "Killing Time", "file_author": "Blair Dunlop & Larkin Poe", "file_cover": null, "release_date": "2013", "album_tracks_dictionary": [{"track_album_title": "Killing Time", "file_album_artist": "Blair Dunlop & Larkin Poe", "file_album_total_track_number": "", "file_album_total_disk_number": "", "file_album_release_year": "2013", "track_title": "Killing Time", "track_artist": "Blair Dunlop", "track_number": "", "track_genre": "'Traditional Country'", "track_lenght": "02:22", "absolute_file_path": "E:\\Music\\Larkin Poe\\EP, Singles\\2013 Killing Time (& Blair Dunlop) (EP) (320)\\01. Killing Time.mp3", "file_format": "mp3"}, {"track_album_title": "Killing Time", "file_album_artist": "Blair Dunlop & Larkin Poe", "file_album_total_track_number": "", "file_album_total_disk_number": "", "file_album_release_year": "2013", "track_title": "I'll Keep It with Mine", "track_artist": "Blair Dunlop", "track_number": "", "track_genre": "'Traditional Country'", "track_lenght": "05:24", "absolute_file_path": "E:\\Music\\Larkin Poe\\EP, Singles\\2013 Killing Time (& Blair Dunlop) (EP) (320)\\02. I'll Keep It with Mine.mp3", "file_format": "mp3"}, {"track_album_title": "Killing Time", "file_album_artist": "Blair Dunlop & Larkin Poe", "file_album_total_track_number": "", "file_album_total_disk_number": "", "file_album_release_year": "2013", "track_title": "Sea of Faces", "track_artist": "Blair Dunlop", "track_number": "", "track_genre": "'Traditional Country'", "track_lenght": "05:25", "absolute_file_path": "E:\\Music\\Larkin Poe\\EP, Singles\\2013 Killing Time (& Blair Dunlop) (EP) (320)\\03. Sea of Faces.mp3", "file_format": "mp3"}, {"track_album_title": "Killing Time", "file_album_artist": "Blair Dunlop & Larkin Poe", "file_album_total_track_number": "", "file_album_total_disk_number": "", "file_album_release_year": "2013", "track_title": "Strangler Fig", "track_artist": "Blair Dunlop", "track_number": "", "track_genre": "'Traditional Country'", "track_lenght": "01:51", "absolute_file_path": "E:\\Music\\Larkin Poe\\EP, Singles\\2013 Killing Time (& Blair Dunlop) (EP) (320)\\04. Strangler Fig.mp3", "file_format": "mp3"}, {"track_album_title": "Killing Time", "file_album_artist": "Blair Dunlop & Larkin Poe", "file_album_total_track_number": "", "file_album_total_disk_number": "", "file_album_release_year": "2013", "track_title": "The Month of January", "track_artist": "Blair Dunlop", "track_number": "", "track_genre": "'Traditional Country'", "track_lenght": "05:03", "absolute_file_path": "E:\\Music\\Larkin Poe\\EP, Singles\\2013 Killing Time (& Blair Dunlop) (EP) (320)\\05. The Month of January.mp3", "file_format": "mp3"}, {"track_album_title": "Killing Time", "file_album_artist": "Blair Dunlop & Larkin Poe", "file_album_total_track_number": "", "file_album_total_disk_number": "", "file_album_release_year": "2013", "track_title": "Lottie", "track_artist": "Blair Dunlop", "track_number": "", "track_genre": "'Traditional Country'", "track_lenght": "03:42", "absolute_file_path": "E:\\Music\\Larkin Poe\\EP, Singles\\2013 Killing Time (& Blair Dunlop) (EP) (320)\\06. Lottie.mp3", "file_format": "mp3"}], "date_added": null, "publisher": null, "album_genre": ["'Traditional Country'"], "date_most_recently_opened": null, "country_of_origin": null, "language": null, "file_size": null}, {"absolute_file_path": null, "file_format": "flac_album", "file_name": "Reskinned", "file_author": "Larkin Poe", "file_cover": null, "release_date": "2016", "album_tracks_dictionary": [{"track_album_title": "Reskinned", "file_album_artist": "Larkin Poe", "file_album_total_track_number": "", "file_album_total_disk_number": "", "file_album_release_year": "2016", "track_title": "Sucker Puncher", "track_artist": "Larkin Poe", "track_number": "", "track_genre": "'Pop/Rock'", "track_lenght": "03:26", "absolute_file_path": "E:\\Music\\Larkin Poe\\Reskinned (2016) FLAC\\01 - Sucker Puncher.flac", "file_format": "flac"}, {"track_album_title": "Reskinned", "file_album_artist": "Larkin Poe", "file_album_total_track_number": "", "file_album_total_disk_number": "", "file_album_release_year": "2016", "track_title": "Trouble In Mind", "track_artist": "Larkin Poe", "track_number": "", "track_genre": "'Pop/Rock'", "track_lenght": "03:39", "absolute_file_path": "E:\\Music\\Larkin Poe\\Reskinned (2016) FLAC\\02 - Trouble In Mind.flac", "file_format": "flac"}, {"track_album_title": "Reskinned", "file_album_artist": "Larkin Poe", "file_album_total_track_number": "", "file_album_total_disk_number": "", "file_album_release_year": "2016", "track_title": "Don't", "track_artist": "Larkin Poe", "track_number": "", "track_genre": "'Pop/Rock'", "track_lenght": "03:01", "absolute_file_path": "E:\\Music\\Larkin Poe\\Reskinned (2016) FLAC\\03 - Don't.flac", "file_format": "flac"}, {"track_album_title": "Reskinned", "file_album_artist": "Larkin Poe", "file_album_total_track_number": "", "file_album_total_disk_number": "", "file_album_release_year": "2016", "track_title": "When God Closes A Door", "track_artist": "Larkin Poe", "track_number": "", "track_genre": "'Pop/Rock'", "track_lenght": "03:25", "absolute_file_path": "E:\\Music\\Larkin Poe\\Reskinned (2016) FLAC\\04 - When God Closes A Door.flac", "file_format": "flac"}, {"track_album_title": "Reskinned", "file_album_artist": "Larkin Poe", "file_album_total_track_number": "", "file_album_total_disk_number": "", "file_album_release_year": "2016", "track_title": "P-R-O-B-L-E-M", "track_artist": "Larkin Poe", "track_number": "", "track_genre": "'Pop/Rock'", "track_lenght": "03:19", "absolute_file_path": "E:\\Music\\Larkin Poe\\Reskinned (2016) FLAC\\05 - P-R-O-B-L-E-M.flac", "file_format": "flac"}, {"track_album_title": "Reskinned", "file_album_artist": "Larkin Poe", "file_album_total_track_number": "", "file_album_total_disk_number": "", "file_album_release_year": "2016", "track_title": "Stubborn Love", "track_artist": "Larkin Poe", "track_number": "", "track_genre": "'Pop/Rock'", "track_lenght": "03:35", "absolute_file_path": "E:\\Music\\Larkin Poe\\Reskinned (2016) FLAC\\06 - Stubborn Love.flac", "file_format": "flac"}, {"track_album_title": "Reskinned", "file_album_artist": "Larkin Poe", "file_album_total_track_number": "", "file_album_total_disk_number": "", "file_album_release_year": "2016", "track_title": "Jailbreak", "track_artist": "Larkin Poe", "track_number": "", "track_genre": "'Pop/Rock'", "track_lenght": "03:46", "absolute_file_path": "E:\\Music\\Larkin Poe\\Reskinned (2016) FLAC\\07 - Jailbreak.flac", "file_format": "flac"}, {"track_album_title": "Reskinned", "file_album_artist": "Larkin Poe", "file_album_total_track_number": "", "file_album_total_disk_number": "", "file_album_release_year": "2016", "track_title": "Banks Of Allatoona", "track_artist": "Larkin Poe", "track_number": "", "track_genre": "'Pop/Rock'", "track_lenght": "03:32", "absolute_file_path": "E:\\Music\\Larkin Poe\\Reskinned (2016) FLAC\\08 - Banks Of Allatoona.flac", "file_format": "flac"}, {"track_album_title": "Reskinned", "file_album_artist": "Larkin Poe", "file_album_total_track_number": "", "file_album_total_disk_number": "", "file_album_release_year": "2016", "track_title": "Blunt", "track_artist": "Larkin Poe", "track_number": "", "track_genre": "'Pop/Rock'", "track_lenght": "03:20", "absolute_file_path": "E:\\Music\\Larkin Poe\\Reskinned (2016) FLAC\\09 - Blunt.flac", "file_format": "flac"}, {"track_album_title": "Reskinned", "file_album_artist": "Larkin Poe", "file_album_total_track_number": "", "file_album_total_disk_number": "", "file_album_release_year": "2016", "track_title": "Sugar High", "track_artist": "Larkin Poe", "track_number": "", "track_genre": "'Pop/Rock'", "track_lenght": "03:06", "absolute_file_path": "E:\\Music\\Larkin Poe\\Reskinned (2016) FLAC\\10 - Sugar High.flac", "file_format": "flac"}, {"track_album_title": "Reskinned", "file_album_artist": "Larkin Poe", "file_album_total_track_number": "", "file_album_total_disk_number": "", "file_album_release_year": "2016", "track_title": "Crown Of Fire", "track_artist": "Larkin Poe", "track_number": "", "track_genre": "'Pop/Rock'", "track_lenght": "03:08", "absolute_file_path": "E:\\Music\\Larkin Poe\\Reskinned (2016) FLAC\\11 - Crown Of Fire.flac", "file_format": "flac"}, {"track_album_title": "Reskinned", "file_album_artist": "Larkin Poe", "file_album_total_track_number": "", "file_album_total_disk_number": "", "file_album_release_year": "2016", "track_title": "Overachiever", "track_artist": "Larkin Poe", "track_number": "", "track_genre": "'Pop/Rock'", "track_lenght": "02:17", "absolute_file_path": "E:\\Music\\Larkin Poe\\Reskinned (2016) FLAC\\12 - Overachiever.flac", "file_format": "flac"}], "date_added": null, "publisher": null, "album_genre": ["'Pop/Rock'"], "date_most_recently_opened": null, "country_of_origin": null, "language": null, "file_size": null}, {"absolute_file_path": null, "file_format": "flac_album", "file_name": "Blood Harmony", "file_author": "Larkin Poe", "file_cover": null, "release_date": "2022", "album_tracks_dictionary": [{"track_album_title": "Blood Harmony", "file_album_artist": "Larkin Poe", "file_album_total_track_number": "", "file_album_total_disk_number": "", "file_album_release_year": "2022", "track_title": "Deep Stays Down", "track_artist": "Larkin Poe", "track_number": "", "track_genre": "'Rock'", "track_lenght": "03:19", "absolute_file_path": "E:\\Music\\Larkin Poe\\Larkin Poe - 2022 - Blood Harmony (FLAC)\\01 - Deep Stays Down.flac", "file_format": "flac"}, {"track_album_title": "Blood Harmony", "file_album_artist": "Larkin Poe", "file_album_total_track_number": "", "file_album_total_disk_number": "", "file_album_release_year": "2022", "track_title": "Bad Spell", "track_artist": "Larkin Poe", "track_number": "", "track_genre": "'Rock'", "track_lenght": "03:15", "absolute_file_path": "E:\\Music\\Larkin Poe\\Larkin Poe - 2022 - Blood Harmony (FLAC)\\02 - Bad Spell.flac", "file_format": "flac"}, {"track_album_title": "Blood Harmony", "file_album_artist": "Larkin Poe", "file_album_total_track_number": "", "file_album_total_disk_number": "", "file_album_release_year": "2022", "track_title": "Georgia Off My Mind", "track_artist": "Larkin Poe", "track_number": "", "track_genre": "'Rock'", "track_lenght": "03:54", "absolute_file_path": "E:\\Music\\Larkin Poe\\Larkin Poe - 2022 - Blood Harmony (FLAC)\\03 - Georgia Off My Mind.flac", "file_format": "flac"}, {"track_album_title": "Blood Harmony", "file_album_artist": "Larkin Poe", "file_album_total_track_number": "", "file_album_total_disk_number": "", "file_album_release_year": "2022", "track_title": "Strike Gold", "track_artist": "Larkin Poe", "track_number": "", "track_genre": "'Rock'", "track_lenght": "03:20", "absolute_file_path": "E:\\Music\\Larkin Poe\\Larkin Poe - 2022 - Blood Harmony (FLAC)\\04 - Strike Gold.flac", "file_format": "flac"}, {"track_album_title": "Blood Harmony", "file_album_artist": "Larkin Poe", "file_album_total_track_number": "", "file_album_total_disk_number": "", "file_album_release_year": "2022", "track_title": "Southern Comfort", "track_artist": "Larkin Poe", "track_number": "", "track_genre": "'Rock'", "track_lenght": "03:47", "absolute_file_path": "E:\\Music\\Larkin Poe\\Larkin Poe - 2022 - Blood Harmony (FLAC)\\05 - Southern Comfort.flac", "file_format": "flac"}, {"track_album_title": "Blood Harmony", "file_album_artist": "Larkin Poe", "file_album_total_track_number": "", "file_album_total_disk_number": "", "file_album_release_year": "2022", "track_title": "Bolt Cutters & The Family Name", "track_artist": "Larkin Poe", "track_number": "", "track_genre": "'Rock'", "track_lenght": "03:15", "absolute_file_path": "E:\\Music\\Larkin Poe\\Larkin Poe - 2022 - Blood Harmony (FLAC)\\06 - Bolt Cutters & The Family Name.flac", "file_format": "flac"}, {"track_album_title": "Blood Harmony", "file_album_artist": "Larkin Poe", "file_album_total_track_number": "", "file_album_total_disk_number": "", "file_album_release_year": "2022", "track_title": "Blood Harmony", "track_artist": "Larkin Poe", "track_number": "", "track_genre": "'Rock'", "track_lenght": "04:05", "absolute_file_path": "E:\\Music\\Larkin Poe\\Larkin Poe - 2022 - Blood Harmony (FLAC)\\07 - Blood Harmony.flac", "file_format": "flac"}, {"track_album_title": "Blood Harmony", "file_album_artist": "Larkin Poe", "file_album_total_track_number": "", "file_album_total_disk_number": "", "file_album_release_year": "2022", "track_title": "Kick the Blues", "track_artist": "Larkin Poe", "track_number": "", "track_genre": "'Rock'", "track_lenght": "03:26", "absolute_file_path": "E:\\Music\\Larkin Poe\\Larkin Poe - 2022 - Blood Harmony (FLAC)\\08 - Kick the Blues.flac", "file_format": "flac"}, {"track_album_title": "Blood Harmony", "file_album_artist": "Larkin Poe", "file_album_total_track_number": "", "file_album_total_disk_number": "", "file_album_release_year": "2022", "track_title": "Might as Well Be Me", "track_artist": "Larkin Poe", "track_number": "", "track_genre": "'Rock'", "track_lenght": "05:10", "absolute_file_path": "E:\\Music\\Larkin Poe\\Larkin Poe - 2022 - Blood Harmony (FLAC)\\09 - Might as Well Be Me.flac", "file_format": "flac"}, {"track_album_title": "Blood Harmony", "file_album_artist": "Larkin Poe", "file_album_total_track_number": "", "file_album_total_disk_number": "", "file_album_release_year": "2022", "track_title": "Summertime Sunset", "track_artist": "Larkin Poe", "track_number": "", "track_genre": "'Rock'", "track_lenght": "05:09", "absolute_file_path": "E:\\Music\\Larkin Poe\\Larkin Poe - 2022 - Blood Harmony (FLAC)\\10 - Summertime Sunset.flac", "file_format": "flac"}, {"track_album_title": "Blood Harmony", "file_album_artist": "Larkin Poe", "file_album_total_track_number": "", "file_album_total_disk_number": "", "file_album_release_year": "2022", "track_title": "Lips as Cold as Diamond", "track_artist": "Larkin Poe", "track_number": "", "track_genre": "'Rock'", "track_lenght": "03:42", "absolute_file_path": "E:\\Music\\Larkin Poe\\Larkin Poe - 2022 - Blood Harmony (FLAC)\\11 - Lips as Cold as Diamond.flac", "file_format": "flac"}], "date_added": null, "publisher": null, "album_genre": ["'Rock'"], "date_most_recently_opened": null, "country_of_origin": null, "language": null, "file_size": null}, {"absolute_file_path": null, "file_format": "mp3_album", "file_name": "Larkin Poe on Audiotree Live", "file_author": "Larkin Poe", "file_cover": null, "release_date": "2017", "album_tracks_dictionary": [{"track_album_title": "Larkin Poe on Audiotree Live", "file_album_artist": "Larkin Poe", "file_album_total_track_number": "", "file_album_total_disk_number": "", "file_album_release_year": "2017", "track_title": "Trouble in Mind (Audiotree Live Version)", "track_artist": "Larkin Poe", "track_number": "", "track_genre": "'Folk-Rock, Americana, Roots Rock'", "track_lenght": "04:13", "absolute_file_path": "E:\\Music\\Larkin Poe\\EP, Singles\\2017 Larkin Poe on Audiotree Live (EP) (L)\\01. Trouble in Mind.mp3", "file_format": "mp3"}, {"track_album_title": "Larkin Poe on Audiotree Live", "file_album_artist": "Larkin Poe", "file_album_total_track_number": "", "file_album_total_disk_number": "", "file_album_release_year": "2017", "track_title": "Run for Your Money (Audiotree Live Version)", "track_artist": "Larkin Poe", "track_number": "", "track_genre": "'Folk-Rock, Americana, Roots Rock'", "track_lenght": "03:31", "absolute_file_path": "E:\\Music\\Larkin Poe\\EP, Singles\\2017 Larkin Poe on Audiotree Live (EP) (L)\\02. Run for Your Money.mp3", "file_format": "mp3"}, {"track_album_title": "Larkin Poe on Audiotree Live", "file_album_artist": "Larkin Poe", "file_album_total_track_number": "", "file_album_total_disk_number": "", "file_album_release_year": "2017", "track_title": "Might as Well Be Me (Audiotree Live Version)", "track_artist": "Larkin Poe", "track_number": "", "track_genre": "'Folk-Rock, Americana, Roots Rock'", "track_lenght": "04:21", "absolute_file_path": "E:\\Music\\Larkin Poe\\EP, Singles\\2017 Larkin Poe on Audiotree Live (EP) (L)\\03. Might as Well Be Me.mp3", "file_format": "mp3"}, {"track_album_title": "Larkin Poe on Audiotree Live", "file_album_artist": "Larkin Poe", "file_album_total_track_number": "", "file_album_total_disk_number": "", "file_album_release_year": "2017", "track_title": "Wanted Woman (Audiotree Live Version)", "track_artist": "Larkin Poe", "track_number": "", "track_genre": "'Folk-Rock, Americana, Roots Rock'", "track_lenght": "05:34", "absolute_file_path": "E:\\Music\\Larkin Poe\\EP, Singles\\2017 Larkin Poe on Audiotree Live (EP) (L)\\04. Wanted Woman.mp3", "file_format": "mp3"}], "date_added": null, "publisher": null, "album_genre": ["'Folk-Rock, Americana, Roots Rock'"], "date_most_recently_opened": null, "country_of_origin": null, "language": null, "file_size": null}, {"absolute_file_path": null, "file_format": "flac_album", "file_name": "Kin", "file_author": "Larkin Poe", "file_cover": null, "release_date": "2014", "album_tracks_dictionary": [{"track_album_title": "Kin", "file_album_artist": "Larkin Poe", "file_album_total_track_number": "", "file_album_total_disk_number": "", "file_album_release_year": "2014", "track_title": "Jailbreak", "track_artist": "Larkin Poe", "track_number": "", "track_genre": "'Folk'", "track_lenght": "03:48", "absolute_file_path": "E:\\Music\\Larkin Poe\\Kin (2014)\\01 - Jailbreak.flac", "file_format": "flac"}, {"track_album_title": "Kin", "file_album_artist": "Larkin Poe", "file_album_total_track_number": "", "file_album_total_disk_number": "", "file_album_release_year": "2014", "track_title": "Don't\\xa0\\xa0", "track_artist": "Larkin Poe", "track_number": "", "track_genre": "'Folk'", "track_lenght": "03:04", "absolute_file_path": "E:\\Music\\Larkin Poe\\Kin (2014)\\02 - Don't\u00a0\u00a0.flac", "file_format": "flac"}, {"track_album_title": "Kin", "file_album_artist": "Larkin Poe", "file_album_total_track_number": "", "file_album_total_disk_number": "", "file_album_release_year": "2014", "track_title": "Stubborn Love\\xa0\\xa0", "track_artist": "Larkin Poe", "track_number": "", "track_genre": "'Folk'", "track_lenght": "03:37", "absolute_file_path": "E:\\Music\\Larkin Poe\\Kin (2014)\\03 - Stubborn Love\u00a0\u00a0.flac", "file_format": "flac"}, {"track_album_title": "Kin", "file_album_artist": "Larkin Poe", "file_album_total_track_number": "", "file_album_total_disk_number": "", "file_album_release_year": "2014", "track_title": "Dandelion\\xa0", "track_artist": "Larkin Poe", "track_number": "", "track_genre": "'Folk'", "track_lenght": "03:30", "absolute_file_path": "E:\\Music\\Larkin Poe\\Kin (2014)\\04 - Dandelion\u00a0.flac", "file_format": "flac"}, {"track_album_title": "Kin", "file_album_artist": "Larkin Poe", "file_album_total_track_number": "", "file_album_total_disk_number": "", "file_album_release_year": "2014", "track_title": "Crown of Fire\\xa0\\xa0", "track_artist": "Larkin Poe", "track_number": "", "track_genre": "'Folk'", "track_lenght": "03:10", "absolute_file_path": "E:\\Music\\Larkin Poe\\Kin (2014)\\05 - Crown of Fire\u00a0\u00a0.flac", "file_format": "flac"}, {"track_album_title": "Kin", "file_album_artist": "Larkin Poe", "file_album_total_track_number": "", "file_album_total_disk_number": "", "file_album_release_year": "2014", "track_title": "\\xa0Elephant\\xa0\\xa0", "track_artist": "Larkin Poe", "track_number": "", "track_genre": "'Folk'", "track_lenght": "03:29", "absolute_file_path": "E:\\Music\\Larkin Poe\\Kin (2014)\\06 - \u00a0Elephant\u00a0\u00a0.flac", "file_format": "flac"}, {"track_album_title": "Kin", "file_album_artist": "Larkin Poe", "file_album_total_track_number": "", "file_album_total_disk_number": "", "file_album_release_year": "2014", "track_title": "High Horse\\xa0\\xa0", "track_artist": "Larkin Poe", "track_number": "", "track_genre": "'Folk'", "track_lenght": "02:59", "absolute_file_path": "E:\\Music\\Larkin Poe\\Kin (2014)\\07 - High Horse\u00a0\u00a0.flac", "file_format": "flac"}, {"track_album_title": "Kin", "file_album_artist": "Larkin Poe", "file_album_total_track_number": "", "file_album_total_disk_number": "", "file_album_release_year": "2014", "track_title": "Sugar High\\xa0", "track_artist": "Larkin Poe", "track_number": "", "track_genre": "'Folk'", "track_lenght": "03:09", "absolute_file_path": "E:\\Music\\Larkin Poe\\Kin (2014)\\08 - Sugar High\u00a0.flac", "file_format": "flac"}, {"track_album_title": "Kin", "file_album_artist": "Larkin Poe", "file_album_total_track_number": "", "file_album_total_disk_number": "", "file_album_release_year": "2014", "track_title": "Jesse\\xa0\\xa0", "track_artist": "Larkin Poe", "track_number": "", "track_genre": "'Folk'", "track_lenght": "03:36", "absolute_file_path": "E:\\Music\\Larkin Poe\\Kin (2014)\\09 - Jesse\u00a0\u00a0.flac", "file_format": "flac"}, {"track_album_title": "Kin", "file_album_artist": "Larkin Poe", "file_album_total_track_number": "", "file_album_total_disk_number": "", "file_album_release_year": "2014", "track_title": "Banks of Allatoona\\xa0\\xa0", "track_artist": "Larkin Poe", "track_number": "", "track_genre": "'Folk'", "track_lenght": "03:34", "absolute_file_path": "E:\\Music\\Larkin Poe\\Kin (2014)\\10 - Banks of Allatoona\u00a0\u00a0.flac", "file_format": "flac"}, {"track_album_title": "Kin", "file_album_artist": "Larkin Poe", "file_album_total_track_number": "", "file_album_total_disk_number": "", "file_album_release_year": "2014", "track_title": "We Intertwine\\xa0", "track_artist": "Larkin Poe", "track_number": "", "track_genre": "'Folk'", "track_lenght": "04:04", "absolute_file_path": "E:\\Music\\Larkin Poe\\Kin (2014)\\11 - We Intertwine\u00a0.flac", "file_format": "flac"}, {"track_album_title": "Kin", "file_album_artist": "Larkin Poe", "file_album_total_track_number": "", "file_album_total_disk_number": "", "file_album_release_year": "2014", "track_title": "Overachiever", "track_artist": "Larkin Poe", "track_number": "", "track_genre": "'Folk'", "track_lenght": "02:19", "absolute_file_path": "E:\\Music\\Larkin Poe\\Kin (2014)\\12 - Overachiever.flac", "file_format": "flac"}], "date_added": null, "publisher": null, "album_genre": ["'Folk'"], "date_most_recently_opened": null, "country_of_origin": null, "language": null, "file_size": null}, {"absolute_file_path": null, "file_format": "mp3_album", "file_name": "The Sound of the Ocean Sound", "file_author": "Larkin Poe & Thom Hell", "file_cover": null, "release_date": "2013", "album_tracks_dictionary": [{"track_album_title": "The Sound of the Ocean Sound", "file_album_artist": "Larkin Poe & Thom Hell", "file_album_total_track_number": "", "file_album_total_disk_number": "", "file_album_release_year": "2013", "track_title": "I Belong to Love", "track_artist": "Larkin Poe & Thom Hell", "track_number": "", "track_genre": "'Folk-Rock, Americana, Roots Rock'", "track_lenght": "04:23", "absolute_file_path": "E:\\Music\\Larkin Poe\\2013 The Sound of the Ocean Sound (& Thom Hell) (L)\\01. I Belong to Love.mp3", "file_format": "mp3"}, {"track_album_title": "The Sound of the Ocean Sound", "file_album_artist": "Larkin Poe & Thom Hell", "file_album_total_track_number": "", "file_album_total_disk_number": "", "file_album_release_year": "2013", "track_title": "Shoulder to Shoulder", "track_artist": "Larkin Poe & Thom Hell", "track_number": "", "track_genre": "'Folk-Rock, Americana, Roots Rock'", "track_lenght": "04:22", "absolute_file_path": "E:\\Music\\Larkin Poe\\2013 The Sound of the Ocean Sound (& Thom Hell) (L)\\02. Shoulder to Shoulder.mp3", "file_format": "mp3"}, {"track_album_title": "The Sound of the Ocean Sound", "file_album_artist": "Larkin Poe & Thom Hell", "file_album_total_track_number": "", "file_album_total_disk_number": "", "file_album_release_year": "2013", "track_title": "P.S. I Love You", "track_artist": "Larkin Poe & Thom Hell", "track_number": "", "track_genre": "'Folk-Rock, Americana, Roots Rock'", "track_lenght": "04:00", "absolute_file_path": "E:\\Music\\Larkin Poe\\2013 The Sound of the Ocean Sound (& Thom Hell) (L)\\03. P.S. I Love You.mp3", "file_format": "mp3"}, {"track_album_title": "The Sound of the Ocean Sound", "file_album_artist": "Larkin Poe & Thom Hell", "file_album_total_track_number": "", "file_album_total_disk_number": "", "file_album_release_year": "2013", "track_title": "Leave", "track_artist": "Larkin Poe & Thom Hell", "track_number": "", "track_genre": "'Folk-Rock, Americana, Roots Rock'", "track_lenght": "02:58", "absolute_file_path": "E:\\Music\\Larkin Poe\\2013 The Sound of the Ocean Sound (& Thom Hell) (L)\\04. Leave.mp3", "file_format": "mp3"}, {"track_album_title": "The Sound of the Ocean Sound", "file_album_artist": "Larkin Poe & Thom Hell", "file_album_total_track_number": "", "file_album_total_disk_number": "", "file_album_release_year": "2013", "track_title": "I Can Almost", "track_artist": "Larkin Poe & Thom Hell", "track_number": "", "track_genre": "'Folk-Rock, Americana, Roots Rock'", "track_lenght": "03:01", "absolute_file_path": "E:\\Music\\Larkin Poe\\2013 The Sound of the Ocean Sound (& Thom Hell) (L)\\05. I Can Almost.mp3", "file_format": "mp3"}, {"track_album_title": "The Sound of the Ocean Sound", "file_album_artist": "Larkin Poe & Thom Hell", "file_album_total_track_number": "", "file_album_total_disk_number": "", "file_album_release_year": "2013", "track_title": "Tired", "track_artist": "Larkin Poe & Thom Hell", "track_number": "", "track_genre": "'Folk-Rock, Americana, Roots Rock'", "track_lenght": "03:46", "absolute_file_path": "E:\\Music\\Larkin Poe\\2013 The Sound of the Ocean Sound (& Thom Hell) (L)\\06. Tired.mp3", "file_format": "mp3"}, {"track_album_title": "The Sound of the Ocean Sound", "file_album_artist": "Larkin Poe & Thom Hell", "file_album_total_track_number": "", "file_album_total_disk_number": "", "file_album_release_year": "2013", "track_title": "As Good As You", "track_artist": "Larkin Poe & Thom Hell", "track_number": "", "track_genre": "'Folk-Rock, Americana, Roots Rock'", "track_lenght": "04:16", "absolute_file_path": "E:\\Music\\Larkin Poe\\2013 The Sound of the Ocean Sound (& Thom Hell) (L)\\07. As Good As You.mp3", "file_format": "mp3"}, {"track_album_title": "The Sound of the Ocean Sound", "file_album_artist": "Larkin Poe & Thom Hell", "file_album_total_track_number": "", "file_album_total_disk_number": "", "file_album_release_year": "2013", "track_title": "Missing Home", "track_artist": "Larkin Poe & Thom Hell", "track_number": "", "track_genre": "'Folk-Rock, Americana, Roots Rock'", "track_lenght": "02:58", "absolute_file_path": "E:\\Music\\Larkin Poe\\2013 The Sound of the Ocean Sound (& Thom Hell) (L)\\08. Missing Home.mp3", "file_format": "mp3"}, {"track_album_title": "The Sound of the Ocean Sound", "file_album_artist": "Larkin Poe & Thom Hell", "file_album_total_track_number": "", "file_album_total_disk_number": "", "file_album_release_year": "2013", "track_title": "Wait For Me", "track_artist": "Larkin Poe & Thom Hell", "track_number": "", "track_genre": "'Folk-Rock, Americana, Roots Rock'", "track_lenght": "03:43", "absolute_file_path": "E:\\Music\\Larkin Poe\\2013 The Sound of the Ocean Sound (& Thom Hell) (L)\\09. Wait For Me.mp3", "file_format": "mp3"}, {"track_album_title": "The Sound of the Ocean Sound", "file_album_artist": "Larkin Poe & Thom Hell", "file_album_total_track_number": "", "file_album_total_disk_number": "", "file_album_release_year": "2013", "track_title": "Widow's Walk", "track_artist": "Larkin Poe & Thom Hell", "track_number": "", "track_genre": "'Folk-Rock, Americana, Roots Rock'", "track_lenght": "03:26", "absolute_file_path": "E:\\Music\\Larkin Poe\\2013 The Sound of the Ocean Sound (& Thom Hell) (L)\\10. Widow's Walk.mp3", "file_format": "mp3"}], "date_added": null, "publisher": null, "album_genre": ["'Folk-Rock, Americana, Roots Rock'"], "date_most_recently_opened": null, "country_of_origin": null, "language": null, "file_size": null}, {"absolute_file_path": null, "file_format": "mp3_album", "file_name": "Venom & Faith", "file_author": "Larkin Poe", "file_cover": null, "release_date": "2018", "album_tracks_dictionary": [{"track_album_title": "Venom & Faith", "file_album_artist": "Larkin Poe", "file_album_total_track_number": "", "file_album_total_disk_number": "", "file_album_release_year": "2018", "track_title": "Sometimes", "track_artist": "Larkin Poe", "track_number": "", "track_genre": "'Blues, Folk Rock'", "track_lenght": "02:52", "absolute_file_path": "E:\\Music\\Larkin Poe\\Venom & Faith\\01 - Sometimes.mp3", "file_format": "mp3"}, {"track_album_title": "Venom & Faith", "file_album_artist": "Larkin Poe", "file_album_total_track_number": "", "file_album_total_disk_number": "", "file_album_release_year": "2018", "track_title": "Bleach Blonde Bottle Blues", "track_artist": "Larkin Poe", "track_number": "", "track_genre": "'Blues, Folk Rock'", "track_lenght": "03:13", "absolute_file_path": "E:\\Music\\Larkin Poe\\Venom & Faith\\02 - Bleach Blonde Bottle Blues.mp3", "file_format": "mp3"}, {"track_album_title": "Venom & Faith", "file_album_artist": "Larkin Poe", "file_album_total_track_number": "", "file_album_total_disk_number": "", "file_album_release_year": "2018", "track_title": "Honey Honey", "track_artist": "Larkin Poe", "track_number": "", "track_genre": "'Blues, Folk Rock'", "track_lenght": "03:29", "absolute_file_path": "E:\\Music\\Larkin Poe\\Venom & Faith\\03 - Honey Honey.mp3", "file_format": "mp3"}, {"track_album_title": "Venom & Faith", "file_album_artist": "Larkin Poe", "file_album_total_track_number": "", "file_album_total_disk_number": "", "file_album_release_year": "2018", "track_title": "Mississippi", "track_artist": "Larkin Poe", "track_number": "", "track_genre": "'Blues, Folk Rock'", "track_lenght": "03:39", "absolute_file_path": "E:\\Music\\Larkin Poe\\Venom & Faith\\04 - Mississippi.mp3", "file_format": "mp3"}, {"track_album_title": "Venom & Faith", "file_album_artist": "Larkin Poe", "file_album_total_track_number": "", "file_album_total_disk_number": "", "file_album_release_year": "2018", "track_title": "California King", "track_artist": "Larkin Poe", "track_number": "", "track_genre": "'Blues, Folk Rock'", "track_lenght": "03:18", "absolute_file_path": "E:\\Music\\Larkin Poe\\Venom & Faith\\05 - California King.mp3", "file_format": "mp3"}, {"track_album_title": "Venom & Faith", "file_album_artist": "Larkin Poe", "file_album_total_track_number": "", "file_album_total_disk_number": "", "file_album_release_year": "2018", "track_title": "Blue Ridge Mountains", "track_artist": "Larkin Poe", "track_number": "", "track_genre": "'Blues, Folk Rock'", "track_lenght": "02:51", "absolute_file_path": "E:\\Music\\Larkin Poe\\Venom & Faith\\06 - Blue Ridge Mountains.mp3", "file_format": "mp3"}, {"track_album_title": "Venom & Faith", "file_album_artist": "Larkin Poe", "file_album_total_track_number": "", "file_album_total_disk_number": "", "file_album_release_year": "2018", "track_title": "Fly Like an Eagle", "track_artist": "Larkin Poe", "track_number": "", "track_genre": "'Blues, Folk Rock'", "track_lenght": "02:43", "absolute_file_path": "E:\\Music\\Larkin Poe\\Venom & Faith\\07 - Fly Like an Eagle.mp3", "file_format": "mp3"}, {"track_album_title": "Venom & Faith", "file_album_artist": "Larkin Poe", "file_album_total_track_number": "", "file_album_total_disk_number": "", "file_album_release_year": "2018", "track_title": "Ain't Gonna Cry", "track_artist": "Larkin Poe", "track_number": "", "track_genre": "'Blues, Folk Rock'", "track_lenght": "03:33", "absolute_file_path": "E:\\Music\\Larkin Poe\\Venom & Faith\\08 - Ain't Gonna Cry.mp3", "file_format": "mp3"}, {"track_album_title": "Venom & Faith", "file_album_artist": "Larkin Poe", "file_album_total_track_number": "", "file_album_total_disk_number": "", "file_album_release_year": "2018", "track_title": "Hard Time Killing Floor Blues", "track_artist": "Larkin Poe", "track_number": "", "track_genre": "'Blues, Folk Rock'", "track_lenght": "03:13", "absolute_file_path": "E:\\Music\\Larkin Poe\\Venom & Faith\\09 - Hard Time Killing Floor Blues.mp3", "file_format": "mp3"}, {"track_album_title": "Venom & Faith", "file_album_artist": "Larkin Poe", "file_album_total_track_number": "", "file_album_total_disk_number": "", "file_album_release_year": "2018", "track_title": "Good and Gone", "track_artist": "Larkin Poe", "track_number": "", "track_genre": "'Blues, Folk Rock'", "track_lenght": "02:35", "absolute_file_path": "E:\\Music\\Larkin Poe\\Venom & Faith\\10 - Good and Gone.mp3", "file_format": "mp3"}], "date_added": null, "publisher": null, "album_genre": ["'Blues, Folk Rock'"], "date_most_recently_opened": null, "country_of_origin": null, "language": null, "file_size": null}, {"absolute_file_path": null, "file_format": "mp3_album", "file_name": "Peach", "file_author": "Larkin Poe", "file_cover": null, "release_date": "2017", "album_tracks_dictionary": [{"track_album_title": "Peach", "file_album_artist": "Larkin Poe", "file_album_total_track_number": "", "file_album_total_disk_number": "", "file_album_release_year": "2017", "track_title": "Come on in My Kitchen", "track_artist": "Larkin Poe", "track_number": "", "track_genre": "'Folk-Rock, Americana, Roots Rock'", "track_lenght": "02:11", "absolute_file_path": "E:\\Music\\Larkin Poe\\2017 Peach (320)\\01. Come on in My Kitchen.mp3", "file_format": "mp3"}, {"track_album_title": "Peach", "file_album_artist": "Larkin Poe", "file_album_total_track_number": "", "file_album_total_disk_number": "", "file_album_release_year": "2017", "track_title": "Freedom", "track_artist": "Larkin Poe", "track_number": "", "track_genre": "'Folk-Rock, Americana, Roots Rock'", "track_lenght": "03:22", "absolute_file_path": "E:\\Music\\Larkin Poe\\2017 Peach (320)\\02. Freedom.mp3", "file_format": "mp3"}, {"track_album_title": "Peach", "file_album_artist": "Larkin Poe", "file_album_total_track_number": "", "file_album_total_disk_number": "", "file_album_release_year": "2017", "track_title": "Black Betty", "track_artist": "Larkin Poe", "track_number": "", "track_genre": "'Folk-Rock, Americana, Roots Rock'", "track_lenght": "02:44", "absolute_file_path": "E:\\Music\\Larkin Poe\\2017 Peach (320)\\03. Black Betty.mp3", "file_format": "mp3"}, {"track_album_title": "Peach", "file_album_artist": "Larkin Poe", "file_album_total_track_number": "", "file_album_total_disk_number": "", "file_album_release_year": "2017", "track_title": "Look Away", "track_artist": "Larkin Poe", "track_number": "", "track_genre": "'Folk-Rock, Americana, Roots Rock'", "track_lenght": "03:24", "absolute_file_path": "E:\\Music\\Larkin Poe\\2017 Peach (320)\\04. Look Away.mp3", "file_format": "mp3"}, {"track_album_title": "Peach", "file_album_artist": "Larkin Poe", "file_album_total_track_number": "", "file_album_total_disk_number": "", "file_album_release_year": "2017", "track_title": "Preachin' Blues", "track_artist": "Larkin Poe", "track_number": "", "track_genre": "'Folk-Rock, Americana, Roots Rock'", "track_lenght": "03:21", "absolute_file_path": "E:\\Music\\Larkin Poe\\2017 Peach (320)\\05. Preachin' Blues.mp3", "file_format": "mp3"}, {"track_album_title": "Peach", "file_album_artist": "Larkin Poe", "file_album_total_track_number": "", "file_album_total_disk_number": "", "file_album_release_year": "2017", "track_title": "Cast Em Out", "track_artist": "Larkin Poe", "track_number": "", "track_genre": "'Folk-Rock, Americana, Roots Rock'", "track_lenght": "02:44", "absolute_file_path": "E:\\Music\\Larkin Poe\\2017 Peach (320)\\06. Cast Em Out.mp3", "file_format": "mp3"}, {"track_album_title": "Peach", "file_album_artist": "Larkin Poe", "file_album_total_track_number": "", "file_album_total_disk_number": "", "file_album_release_year": "2017", "track_title": "Pink & Red", "track_artist": "Larkin Poe", "track_number": "", "track_genre": "'Folk-Rock, Americana, Roots Rock'", "track_lenght": "03:17", "absolute_file_path": "E:\\Music\\Larkin Poe\\2017 Peach (320)\\07. Pink & Red.mp3", "file_format": "mp3"}, {"track_album_title": "Peach", "file_album_artist": "Larkin Poe", "file_album_total_track_number": "", "file_album_total_disk_number": "", "file_album_release_year": "2017", "track_title": "John the Revelator", "track_artist": "Larkin Poe", "track_number": "", "track_genre": "'Folk-Rock, Americana, Roots Rock'", "track_lenght": "03:19", "absolute_file_path": "E:\\Music\\Larkin Poe\\2017 Peach (320)\\08. John the Revelator.mp3", "file_format": "mp3"}, {"track_album_title": "Peach", "file_album_artist": "Larkin Poe", "file_album_total_track_number": "", "file_album_total_disk_number": "", "file_album_release_year": "2017", "track_title": "Wanted Woman / AC/DC", "track_artist": "Larkin Poe", "track_number": "", "track_genre": "'Folk-Rock, Americana, Roots Rock'", "track_lenght": "04:50", "absolute_file_path": "E:\\Music\\Larkin Poe\\2017 Peach (320)\\09. Wanted Woman  ACDC.mp3", "file_format": "mp3"}, {"track_album_title": "Peach", "file_album_artist": "Larkin Poe", "file_album_total_track_number": "", "file_album_total_disk_number": "", "file_album_release_year": "2017", "track_title": "Tom Devil", "track_artist": "Larkin Poe", "track_number": "", "track_genre": "'Folk-Rock, Americana, Roots Rock'", "track_lenght": "02:44", "absolute_file_path": "E:\\Music\\Larkin Poe\\2017 Peach (320)\\10. Tom Devil.mp3", "file_format": "mp3"}], "date_added": null, "publisher": null, "album_genre": ["'Folk-Rock, Americana, Roots Rock'"], "date_most_recently_opened": null, "country_of_origin": null, "language": null, "file_size": null}, {"absolute_file_path": null, "file_format": "flac_album", "file_name": "Paint The Roses (Live In Concert)", "file_author": "Nu Deco Ensemble", "file_cover": null, "release_date": "2021", "album_tracks_dictionary": [{"track_album_title": "Paint The Roses (Live In Concert)", "file_album_artist": "Nu Deco Ensemble", "file_album_total_track_number": "", "file_album_total_disk_number": "", "file_album_release_year": "2021", "track_title": "Sometimes ", "track_artist": "Nu Deco Ensemble", "track_number": "", "track_genre": "'Blues'", "track_lenght": "03:08", "absolute_file_path": "E:\\Music\\Larkin Poe\\2021\\01 - Sometimes (live In Concert).flac", "file_format": "flac"}, {"track_album_title": "Paint The Roses (Live In Concert)", "file_album_artist": "Nu Deco Ensemble", "file_album_total_track_number": "", "file_album_total_disk_number": "", "file_album_release_year": "2021", "track_title": "Back Down South / Blue Sky ", "track_artist": "Nu Deco Ensemble", "track_number": "", "track_genre": "'Blues'", "track_lenght": "04:58", "absolute_file_path": "E:\\Music\\Larkin Poe\\2021\\02 - Back Down South _ Blue Sky (live In Concert).flac", "file_format": "flac"}, {"track_album_title": "Paint The Roses (Live In Concert)", "file_album_artist": "Nu Deco Ensemble", "file_album_total_track_number": "", "file_album_total_disk_number": "", "file_album_release_year": "2021", "track_title": "Mad As A Hatter ", "track_artist": "Nu Deco Ensemble", "track_number": "", "track_genre": "'Blues'", "track_lenght": "05:12", "absolute_file_path": "E:\\Music\\Larkin Poe\\2021\\03 - Mad As A Hatter (live In Concert).flac", "file_format": "flac"}, {"track_album_title": "Paint The Roses (Live In Concert)", "file_album_artist": "Nu Deco Ensemble", "file_album_total_track_number": "", "file_album_total_disk_number": "", "file_album_release_year": "2021", "track_title": "Danger Angel ", "track_artist": "Nu Deco Ensemble", "track_number": "", "track_genre": "'Blues'", "track_lenght": "02:54", "absolute_file_path": "E:\\Music\\Larkin Poe\\2021\\04 - Danger Angel (live In Concert).flac", "file_format": "flac"}, {"track_album_title": "Paint The Roses (Live In Concert)", "file_album_artist": "Nu Deco Ensemble", "file_album_total_track_number": "", "file_album_total_disk_number": "", "file_album_release_year": "2021", "track_title": "Tears Of Blue To Gold ", "track_artist": "Nu Deco Ensemble", "track_number": "", "track_genre": "'Blues'", "track_lenght": "04:21", "absolute_file_path": "E:\\Music\\Larkin Poe\\2021\\05 - Tears Of Blue To Gold (live In Concert).flac", "file_format": "flac"}, {"track_album_title": "Paint The Roses (Live In Concert)", "file_album_artist": "Nu Deco Ensemble", "file_album_total_track_number": "", "file_album_total_disk_number": "", "file_album_release_year": "2021", "track_title": "Every Bird That Flies", "track_artist": "Nu Deco Ensemble", "track_number": "", "track_genre": "'Blues'", "track_lenght": "04:16", "absolute_file_path": "E:\\Music\\Larkin Poe\\2021\\06 - Every Bird That Flies (live In Concert).flac", "file_format": "flac"}, {"track_album_title": "Paint The Roses (Live In Concert)", "file_album_artist": "Nu Deco Ensemble", "file_album_total_track_number": "", "file_album_total_disk_number": "", "file_album_release_year": "2021", "track_title": "She's A Self Made Man ", "track_artist": "Nu Deco Ensemble", "track_number": "", "track_genre": "'Blues'", "track_lenght": "04:24", "absolute_file_path": "E:\\Music\\Larkin Poe\\2021\\07 - She's A Self Made Man (live In Concert).flac", "file_format": "flac"}], "date_added": null, "publisher": null, "album_genre": ["'Blues'"], "date_most_recently_opened": null, "country_of_origin": null, "language": null, "file_size": null}, {"absolute_file_path": null, "file_format": "flac_album", "file_name": "Kindred Spirits", "file_author": "Larkin Poe", "file_cover": null, "release_date": "2020", "album_tracks_dictionary": [{"track_album_title": "Kindred Spirits", "file_album_artist": "Larkin Poe", "file_album_total_track_number": "", "file_album_total_disk_number": "", "file_album_release_year": "2020", "track_title": "Hellhound On My Trail", "track_artist": "Larkin Poe", "track_number": "", "track_genre": "", "track_lenght": "0:43", "absolute_file_path": "E:\\Music\\Larkin Poe\\Larkin Poe - Kindred Spirits (2020) - WEB FLAC\\01. Hellhound On My Trail.flac", "file_format": "flac"}, {"track_album_title": "Kindred Spirits", "file_album_artist": "Larkin Poe", "file_album_total_track_number": "", "file_album_total_disk_number": "", "file_album_release_year": "2020", "track_title": "Fly Away", "track_artist": "Larkin Poe", "track_number": "", "track_genre": "", "track_lenght": "03:30", "absolute_file_path": "E:\\Music\\Larkin Poe\\Larkin Poe - Kindred Spirits (2020) - WEB FLAC\\02. Fly Away.flac", "file_format": "flac"}, {"track_album_title": "Kindred Spirits", "file_album_artist": "Larkin Poe", "file_album_total_track_number": "", "file_album_total_disk_number": "", "file_album_release_year": "2020", "track_title": "Rockin\u2019 In The Free World", "track_artist": "Larkin Poe", "track_number": "", "track_genre": "", "track_lenght": "04:14", "absolute_file_path": "E:\\Music\\Larkin Poe\\Larkin Poe - Kindred Spirits (2020) - WEB FLAC\\03. Rockin\u2019 In The Free World.flac", "file_format": "flac"}, {"track_album_title": "Kindred Spirits", "file_album_artist": "Larkin Poe", "file_album_total_track_number": "", "file_album_total_disk_number": "", "file_album_release_year": "2020", "track_title": "(You\u2019re The) Devil In Disguise", "track_artist": "Larkin Poe", "track_number": "", "track_genre": "", "track_lenght": "03:07", "absolute_file_path": "E:\\Music\\Larkin Poe\\Larkin Poe - Kindred Spirits (2020) - WEB FLAC\\04. (You\u2019re The) Devil In Disguise.flac", "file_format": "flac"}, {"track_album_title": "Kindred Spirits", "file_album_artist": "Larkin Poe", "file_album_total_track_number": "", "file_album_total_disk_number": "", "file_album_release_year": "2020", "track_title": "In The Air Tonight", "track_artist": "Larkin Poe", "track_number": "", "track_genre": "", "track_lenght": "03:21", "absolute_file_path": "E:\\Music\\Larkin Poe\\Larkin Poe - Kindred Spirits (2020) - WEB FLAC\\05. In The Air Tonight.flac", "file_format": "flac"}, {"track_album_title": "Kindred Spirits", "file_album_artist": "Larkin Poe", "file_album_total_track_number": "", "file_album_total_disk_number": "", "file_album_release_year": "2020", "track_title": "Nights In White Satin", "track_artist": "Larkin Poe", "track_number": "", "track_genre": "", "track_lenght": "03:40", "absolute_file_path": "E:\\Music\\Larkin Poe\\Larkin Poe - Kindred Spirits (2020) - WEB FLAC\\06. Nights In White Satin.flac", "file_format": "flac"}, {"track_album_title": "Kindred Spirits", "file_album_artist": "Larkin Poe", "file_album_total_track_number": "", "file_album_total_disk_number": "", "file_album_release_year": "2020", "track_title": "Who Do You Love", "track_artist": "Larkin Poe", "track_number": "", "track_genre": "", "track_lenght": "02:15", "absolute_file_path": "E:\\Music\\Larkin Poe\\Larkin Poe - Kindred Spirits (2020) - WEB FLAC\\07. Who Do You Love.flac", "file_format": "flac"}, {"track_album_title": "Kindred Spirits", "file_album_artist": "Larkin Poe", "file_album_total_track_number": "", "file_album_total_disk_number": "", "file_album_release_year": "2020", "track_title": "Take What You Want", "track_artist": "Larkin Poe", "track_number": "", "track_genre": "", "track_lenght": "02:59", "absolute_file_path": "E:\\Music\\Larkin Poe\\Larkin Poe - Kindred Spirits (2020) - WEB FLAC\\08. Take What You Want.flac", "file_format": "flac"}, {"track_album_title": "Kindred Spirits", "file_album_artist": "Larkin Poe", "file_album_total_track_number": "", "file_album_total_disk_number": "", "file_album_release_year": "2020", "track_title": "Ramblin\u2019 Man", "track_artist": "Larkin Poe", "track_number": "", "track_genre": "", "track_lenght": "02:43", "absolute_file_path": "E:\\Music\\Larkin Poe\\Larkin Poe - Kindred Spirits (2020) - WEB FLAC\\09. Ramblin\u2019 Man.flac", "file_format": "flac"}, {"track_album_title": "Kindred Spirits", "file_album_artist": "Larkin Poe", "file_album_total_track_number": "", "file_album_total_disk_number": "", "file_album_release_year": "2020", "track_title": "Bell Bottom Blues", "track_artist": "Larkin Poe", "track_number": "", "track_genre": "", "track_lenght": "03:41", "absolute_file_path": "E:\\Music\\Larkin Poe\\Larkin Poe - Kindred Spirits (2020) - WEB FLAC\\10. Bell Bottom Blues.flac", "file_format": "flac"}, {"track_album_title": "Kindred Spirits", "file_album_artist": "Larkin Poe", "file_album_total_track_number": "", "file_album_total_disk_number": "", "file_album_release_year": "2020", "track_title": "Crocodile Rock", "track_artist": "Larkin Poe", "track_number": "", "track_genre": "", "track_lenght": "03:11", "absolute_file_path": "E:\\Music\\Larkin Poe\\Larkin Poe - Kindred Spirits (2020) - WEB FLAC\\11. Crocodile Rock.flac", "file_format": "flac"}], "date_added": null, "publisher": null, "album_genre": [""], "date_most_recently_opened": null, "country_of_origin": null, "language": null, "file_size": null}]